sundash/__init__.py
sundash/app.py
sundash/html.py
sundash/logging.py
sundash/messages.py
sundash/scheduler.py
sundash/server.py
sundash/sessions.py
sundash/tables.py
sundash/utils.py
sundash/web/client.js
sundash/web/favicon.ico
sundash/web/index.html
sundash/web/style.css
sundash-0.0.7.dist-info/LICENSE
sundash-0.0.7.dist-info/METADATA
sundash-0.0.7.dist-info/WHEEL
sundash-0.0.7.dist-info/RECORD
