Metadata-Version: 2.1
Name: sundash
Version: 0.0.7
Summary: Python & JS micro framework for realtime web UI applications
Home-page: https://github.com/ruthus18/sundash
License: MIT
Keywords: backend,frontend,server,client,ws,framework
Author: Danil Tryapchev
Author-email: ruthus18@gmail.com
Requires-Python: >=3.12,<4.0
Classifier: License :: OSI Approved :: MIT License
Classifier: Programming Language :: Python :: 3
Classifier: Programming Language :: Python :: 3.12
Requires-Dist: colorlog (>=6.8.2,<7.0.0)
Requires-Dist: starlette (>=0.37.2,<0.38.0)
Requires-Dist: uvicorn (>=0.29.0,<0.30.0)
Requires-Dist: websockets (>=12.0,<13.0)
Project-URL: Repository, https://github.com/ruthus18/sundash
